gitmini/__init__.py
gitmini/__main__.py
gitmini/cli.py
gitmini/utils.py
gitmini/classes/Blob.py
gitmini/classes/Commit.py
gitmini/classes/HEAD.py
gitmini/classes/Ignore.py
gitmini/classes/Index.py
gitmini/classes/Repo.py
gitmini/classes/Tree.py
gitmini/classes/__init__.py
gitmini/commands/__init__.py
gitmini/commands/add.py
gitmini/commands/branch.py
gitmini/commands/checkout.py
gitmini/commands/commit.py
gitmini/commands/init.py
gitmini/commands/log.py
gitmini-0.1.5.dist-info/licenses/LICENSE
tests/__init__.py
tests/test_helpers.py
tests/test_smoke.py
tests/test_utils.py
tests/classes/__init__.py
tests/classes/test_Blob.py
tests/classes/test_Commit.py
tests/classes/test_HEAD.py
tests/classes/test_Index.py
tests/classes/test_Repo.py
tests/classes/test_Tree.py
tests/commands/__init__.py
tests/commands/test_add.py
tests/commands/test_branch.py
tests/commands/test_checkout.py
tests/commands/test_commit.py
tests/commands/test_init.py
tests/commands/test_log.py
gitmini-0.1.5.dist-info/METADATA
gitmini-0.1.5.dist-info/WHEEL
gitmini-0.1.5.dist-info/entry_points.txt
gitmini-0.1.5.dist-info/top_level.txt
gitmini-0.1.5.dist-info/RECORD
