Metadata-Version: 2.4
Name: gitmini
Version: 0.1.5
Summary: A lightweight CLI version control system that replicates core Git commands from scratch.
Author-email: James David Furtado <jamesdfurtado@gmail.com>
License: Copyright 2025 James David Furtado
Keywords: version control,git,cli,developer tool
Classifier: Programming Language :: Python :: 3
Classifier: License :: OSI Approved :: MIT License
Classifier: Operating System :: OS Independent
Classifier: Development Status :: 4 - Beta
Classifier: Intended Audience :: Developers
Classifier: Topic :: Software Development :: Version Control
Requires-Python: >=3.7
License-File: LICENSE
Dynamic: license-file
